
{
  "registry_name": "scalinghealth:power_crystal_stone_deepslate",
  "worldgen/configured_feature": {
    "config": {
      "targets": [
        {
          "target": {
            "tag": "minecraft:deepslate_ore_replaceables",
            "predicate_type": "minecraft:tag_match"
          },
          "state": {
            "Name": "scalinghealth:deepslate_power_crystal_ore"
          }
        }
      ],
      "size": 4,
      "discard_chance_on_air_exposure": 0.0
    },
    "type": "minecraft:ore"
  }
}